setup.py
mplstyler/__init__.py
mplstyler/styles.py
mplstyler.egg-info/PKG-INFO
mplstyler.egg-info/SOURCES.txt
mplstyler.egg-info/dependency_links.txt
mplstyler.egg-info/requires.txt
mplstyler.egg-info/top_level.txt