Metadata-Version: 1.1
Name: mplstyler
Version: 0.1
Summary: An API for assigning consistent marker styles to plots. Assign colours, markers, line-styles to labels and re-use on subsequent plots.
Home-page: https://github.com/mfitzp/mplstyler
Author: Martin Fitzpatrick
Author-email: martin.fitzpatrick@gmail.com
License: GPL
Download-URL: https://github.com/mfitzp/mplstyler/zipball/master
Keywords: bioinformatics research analysis science
Platform: UNKNOWN
Classifier: Development Status :: 4 - Beta
Classifier: Natural Language :: English
Classifier: Operating System :: OS Independent
Classifier: Programming Language :: Python :: 2
Classifier: License :: OSI Approved :: GNU General Public License v3 (GPLv3)
Classifier: Topic :: Scientific/Engineering :: Bio-Informatics
Classifier: Topic :: Education
Classifier: Intended Audience :: Science/Research
Classifier: Intended Audience :: Education
